Workbook

Sheet Variables
A1: # | B1: Priority | C1: Group | D1: Variable | E1: Business definition | F1: Calculation (simplified) | G1: Data attributes / data points | H1: Source system | I1: Window(s) | J1: Data type / unit | K1: Considerations & exclusions | L1: Alert threshold (illustrative) | M1: Predictive strength | N1: Feasibility | O1: Feasibility rationale | P1: Priority rationale | Q1: Detailed logic (for data engineering)
A2: 1 | B2: P1 | C2: Balances & AUM | D2: aum_outflow | E2: Money the client moves out of investment accounts by their own decision, excluding market gains or losses. | F2: Money out of investment accounts − money in, last 90d (0 if negative) | G2: • household_id, account_id, account_type • transaction_date, settlement_date • transaction_type (withdrawal, transfer out, ACATS, distribution, contribution, reinvestment) • transaction_amount • counterparty flag (internal vs. external) • daily account market value | H2: Wealth / custody | I2: 30d, 90d | J2: Amount ($) and % | K2: Exclude transfers between accounts of the same household, bank fees, tax withholdings and RMDs (scheduled required minimum distributions). | L2: aum_outflow_pct_90d > 10% | M2: High | N2: Medium | O2: Requires classifying custody transaction codes into outflow vs. contribution. | P2: Direct measure of asset flight; core input for soft churn. | Q2: aum_outflow_W = max(0, Σ investment outflows − Σ contributions) over (t−W, t]. Outflows = cash withdrawals, outgoing cash or securities transfers (incl. ACATS) and distributions paid outside the bank. Contributions = deposits, incoming transfers and reinvestments. Relative version: aum_outflow_pct_W = aum_outflow_W ÷ average daily AUM over the same window.
A3: 2 | B3: P1 | C3: Balances & AUM | D3: deposit_balance_change_pct | E3: How much the money the client keeps in deposits went up or down versus the prior period of the same length. | F3: Avg deposit balance (last 90d) ÷ avg deposit balance (prior 90d) − 1 | G3: • household_id, account_id • product_type (checking, savings, MM, CD) • balance_date • end-of-day ledger balance | H3: Core banking | I3: 30d, 90d, 180d | J3: % (fraction) | K3: If the prior-period balance is below the minimum (e.g. $10,000) → null, to avoid extreme %. Exclude internal transfers between household accounts. | L3: ≤ −25% over 90d | M3: High | N3: High | O3: Daily balances are standard in core banking. | P3: Classic attrition signal and simple to build. | Q3: = (average daily deposit balance over (t−W, t] ÷ average daily deposit balance over (t−2W, t−W]) − 1. Deposits = checking, savings, money market and CDs, summed at household level.
A4: 3 | B4: P1 | C4: Recurring deposits & flows | D4: salary_deposit_stopped_flag | E4: The client stopped receiving their payroll at Citizens. It usually means they moved their primary bank. | F4: 1 if a regular payroll deposit has not arrived in the last 45 days | G4: • household_id, account_id • ACH credit transactions: date, amount • SEC code, company ID / originator name • transaction description | H4: Core banking (ACH) | I4: 45d | J4: Binary | K4: Exclude reported retirement, death and known leaves. For monthly payroll, use 1.5× the usual interval instead of a fixed 45d. | L4: = 1 | M4: Very high | N4: Medium | O4: Requires a recurring-pattern detection routine on ACH data. | P4: One of the strongest early signals; data exists. | Q4: 1) Identify payroll: ACH credits with payroll code (SEC PPD / description such as PAYROLL or DIR DEP) from the same originator, with ≥3 occurrences in 6m and regular periodicity (coefficient of variation of intervals < 0.25). 2) Flag = 1 if the pattern existed as of t−45d and there is no credit from that originator in (t−45d, t]. 3) If a new payroll arrives for ≥50% of the prior amount (job change) → Flag = 0.
A5: 4 | B5: P1 | C5: Recurring deposits & flows | D5: recurring_deposit_stopped_flag | E5: A significant recurring income stream stopped arriving (payroll, pension, dividends, trust distributions, rental income). | F5: 1 if any regular income (payroll, pension, dividends, trust distributions) has not arrived in the last 45 days | G5: • household_id, account_id • credit transactions: date, amount • originator / payer ID and name • transaction type (ACH, wire, check, dividend) | H5: Core banking + custody | I5: 45d or 1.5× interval | J5: Binary | K5: Quarterly streams (dividends) need a 1.5 × 90d window. Also store the type of stream that stopped, to explain the alert. | L5: = 1 | M5: High | N5: Medium | O5: Same recurring-pattern routine, extended to all streams. | P5: Aggregate signal; deck rule. | Q5: 1) Identify each recurring stream by originator, with ≥3 occurrences in 12m and regular periodicity. 2) Keep only streams representing ≥10% of total recurring income. 3) Flag = 1 if any of them does not arrive within 1.5× its usual interval (minimum 45d).
A6: 5 | B6: P1 | C6: Recurring deposits & flows | D6: recurring_deposit_change_pct | E6: How much the client's recurring income fell versus its normal level, even if it did not stop completely. | F6: Recurring deposits (last 30d) ÷ monthly average of the prior 6 months − 1 | G6: • Output of the recurring-stream detection (stream_id, frequency) • credit transactions: date, amount | H6: Core banking | I6: 30d vs. 6m baseline | J6: % (fraction) | K6: Null if no recurring streams are identified. Deck rule. | L6: ≤ −40% | M6: High | N6: Medium | O6: Depends on the recurring-stream routine. | P6: Deck rule; captures partial redirection of income. | Q6: = Σ recurring deposits over (t−30d, t] ÷ average monthly recurring deposits over (t−210d, t−30d] − 1. Quarterly streams are converted to a monthly amount (amount ÷ 3) to avoid false drops.
A7: 6 | B7: P1 | C7: Recurring deposits & flows | D7: net_deposit_flow | E7: Net balance of money entering and leaving the client's deposits. Negative = the client is taking out more than they put in. | F7: Money into deposits − money out of deposits, last 90d | G7: • household_id, account_id • transaction_date, amount, debit/credit indicator • internal-transfer flag | H7: Core banking | I7: 30d, 90d | J7: Amount ($) and % | K7: Exclude internal transfers between accounts of the same household (including deposit ↔ investment). Partially overlaps with net_external_flow. | L7: pct_90d ≤ −15% | M7: High | N7: High | O7: Standard transaction data. | P7: Cheap to build and a baseline for other flow variables. | Q7: = Σ credits − Σ debits on deposit accounts over (t−W, t], at household level. Relative version: net_deposit_flow_pct = net_deposit_flow ÷ average daily balance of the window.
A8: 7 | B8: P1 | C8: Transfers | D8: external_transfer_pct_of_balance | E8: Share of the client's money sent to other institutions. The most direct signal that the client is moving the relationship. | F8: Money sent to other institutions (last 60d) ÷ average balance | G8: • household_id, account_id • outgoing wires and ACH: date, amount • beneficiary bank ABA / SWIFT, beneficiary name/account • payment purpose / SEC code (to exclude billers, taxes) • average daily balance | H8: Core banking + payments | I8: 30d, 60d | J8: % (fraction) | K8: Exclude payments to merchants and billers, taxes (IRS / state), loan payments to Citizens and identified recurring donations. Deck rule. | L8: > 15% over 60d | M8: Very high | N8: High | O8: Wire and ACH data are available; exclusion rules need to be coded. | P8: Strongest day-1 predictor. | Q8: = Σ outgoing external transfers over (t−60d, t] ÷ average daily balance (deposits + cash in investment accounts) over the same window. External transfer = outgoing wire, client-originated ACH to an external account, or transfer to the client's own account at another bank.
A9: 8 | B9: P1 | C9: Transfers | D9: new_external_destinations | E9: Number of new external accounts the client started sending money to. Opening new destinations is often the first step in moving. | F9: Number of external accounts that received money for the first time in the last 30d | G9: • outgoing wires and ACH: date, amount • beneficiary ABA / SWIFT + account number or beneficiary ID • 12m+ payee history | H9: Core banking + payments | I9: 30d, 90d | J9: Integer | K9: Count only destinations receiving ≥ a minimum amount (e.g. $10,000 cumulative) to exclude small payments. | L9: ≥ 1 in 30d | M9: High | N9: High | O9: Requires 12m+ of payee history, which is usually retained. | P9: Earliest behavioral sign of a move. | Q9: = number of distinct destinations (routing + account, or wire beneficiary) that received funds over (t−W, t] and do not appear in the 12 months before the window.
A10: 9 | B10: P1 | C10: Investments | D10: investment_redemption_pct | E10: Share of their investments the client sold without reinvesting. | F10: (Sales − purchases, last 90d) ÷ average AUM | G10: • household_id, account_id • trades: trade_date, side (buy/sell/redeem), amount • order origin (client vs. advisor / model rebalance) • daily AUM | H10: Wealth / custody | I10: 90d | J10: % (fraction) | K10: Exclude RMDs, agreed scheduled withdrawals and advisor-driven rebalancing sales. | L10: > 20% | M10: High | N10: Medium | O10: Trade data exists; order origin may need mapping. | P10: Main disinvestment signal before an outflow. | Q10: = max(0, Σ sales and redemptions − Σ purchases) over (t−90d, t] ÷ average daily AUM of the window. Net selling is measured, so a rebalance (sell and repurchase) does not count.
A11: 10 | B11: P1 | C11: Relationship & closures | D11: products_closed | E11: Number of products the client closed. Closing products is a visible contraction of the relationship. | F11: Number of products closed in the last 90d | G11: • household_id, account_id • product code / product family • account open and close dates, close reason | H11: Core banking + wealth | I11: 90d, 180d | J11: Integer | K11: Exclude renewed natural maturities (renewed CD), loans paid at term and product conversions or upgrades. | L11: ≥ 1 | M11: Very high | N11: High | O11: Account status and close dates are standard. | P11: Direct evidence of soft churn in progress. | Q11: = number of distinct products (by product code) with close date over (t−W, t], at household level.
A12: 11 | B12: P1 | C12: Banker | D12: banker_change_6m_flag | E12: The client's banker changed in the last 6 months. Advisor change is one of the strongest leading indicators of asset flight. | F12: 1 if the primary banker changed in the last 6 months | G12: • household_id • banker assignment history: banker_id, role (primary), start and end dates • reassignment reason | H12: CRM | I12: 6m | J12: Binary | K12: Exclude temporary coverage (< 30 days, vacations or leaves). | L12: = 1 | M12: Very high | N12: High | O12: Assignment history is kept in CRM. | P12: Top leading indicator; easy to build. | Q12: = 1 if the primary assigned banker_id changed over (t−6m, t]. The reason is also stored: banker departure, book rebalancing or client request.
A13: 12 | B13: P1 | C13: Banker | D13: contact_gap_ratio | E13: How long the client has gone without meaningful contact, relative to the contact frequency agreed for them. | F13: Days since last meaningful contact ÷ agreed contact frequency (days) | G13: • CRM activities: type, date, direction, participants • call logs: date, duration • message threads: sent/replied timestamps • agreed cadence / service tier | H13: CRM + telephony | I13: At snapshot | J13: Continuous (ratio) | K13: Exclude automated messages, marketing campaigns and mass mailings. Deck rule. | L13: > 2.0 | M13: High | N13: Medium | O13: Depends on the completeness of activity logging in CRM. | P13: Deck rule; main measure of neglect. | Q13: = days since last meaningful contact ÷ agreed cadence in days. Meaningful contact = meeting, call ≥ 5 min, or banker message with a client reply. Cadence per service model (e.g. UHNW 30d, HNW 90d) or as agreed with the client.
... A38: 37 | B38: P3 | C38: External & composite | D38: bureau_new_mortgage_elsewhere | E38: The client opened a mortgage or HELOC with another institution. It often pulls deposits and other products with it. | F38: 1 if the credit bureau shows a new mortgage with another lender in the last 6 months | G38: • bureau tradelines: account type, creditor, open date, balance • consumer consent / permissible-purpose record | H38: Credit bureau | I38: 6m | J38: Binary | K38: Requires permissible purpose under FCRA (e.g. existing-account review) and legal validation before use. | L38: = 1 | M38: High | N38: Low | O38: Legal path and bureau contract needed. | P38: Strong, but blocked until legal clearance. | Q38: = 1 if the credit bureau report shows a mortgage or HELOC tradeline with open date over (t−6m, t] and a creditor other than Citizens.

Sheet Priority & feasibility
A1: How priority and feasibility are defined
A3: 1 · Predictive strength (expert prior, to be validated with IV / SHAP)
A4: Level | B4: Definition
A5: Very high | B5: Direct precursor of exit: the client is already moving money, closing products, or lost their banker.
A6: High | B6: Clear and consistent deterioration of the relationship: contraction, neglect or serious friction.
A8: 2 · Feasibility (how hard it is to build the variable with Citizens' data)
A9: Level | B9: Definition | C9: Typical examples
A10: High | B10: Raw data already exists in core systems (core banking, CRM, complaints) and the logic is a direct aggregation. | C10: Balances, account closures, banker assignment history, complaint dates
A11: Medium | B11: Data exists but needs derived logic, entity linkage, a reference catalog, or depends on data-quality checks. | C11: Recurring-deposit detection, TWR index, competitor ABA catalog, CRM activity completeness
A12: Low | B12: Requires a new data source, a field not captured today, legal clearance, or the Client Assistant in production. | C12: Bureau data (FCRA), Assistant NLP signals, 'cancelled by' field in CRM
A14: 3 · Priority (combines predictive strength, feasibility and redundancy)
A15: Priority | B15: Rule | C15: Meaning for the build plan
A16: P1 | B16: Very high or high predictive strength + High or Medium feasibility + not redundant with another variable in the set. | C16: Wave 1: extract and build first; core of the first scorecard and ML baseline.
A17: P2 | B17: High predictive strength but (a) redundant with a P1 variable, (b) applies only to a subset of households, or (c) needs a catalog or data-quality work first. | C17: Wave 2: build after P1; keep if it adds IV / SHAP lift over its P1 pair.
A18: P3 | B18: Low feasibility (no history, new field, or legal path pending), or redundant and harder to build. | C18: Wave 3: build going forward or once the blocker is cleared; enters at retraining.

Sheet Summary
A1: Summary by group and priority (formulas on Variables sheet)
A3: Group | B3: P1 | C3: P2 | D3: P3 | E3: Total | F3: High feasibility | G3: Medium feasibility | H3: Low feasibility
A4: Balances & AUM | B4: =COUNTIFS(Variables!$C$2:$C$38,$A4,Variables!$B$2:$B$38,"P1") -> 2 | C4: =COUNTIFS(Variables!$C$2:$C$38,$A4,Variables!$B$2:$B$38,"P2") -> 2 | D4: =COUNTIFS(Variables!$C$2:$C$38,$A4,Variables!$B$2:$B$38,"P3") -> 0 | E4: =SUM(B4:D4) -> 4 | F4: =COUNTIFS(Variables!$C$2:$C$38,$A4,Variables!$N$2:$N$38,"High") -> 2 | G4: =COUNTIFS(Variables!$C$2:$C$38,$A4,Variables!$N$2:$N$38,"Medium") -> 2 | H4: =COUNTIFS(Variables!$C$2:$C$38,$A4,Variables!$N$2:$N$38,"Low") -> 0
A5: Recurring deposits & flows | B5: =COUNTIFS(Variables!$C$2:$C$38,$A5,Variables!$B$2:$B$38,"P1") -> 4 | C5: =COUNTIFS(Variables!$C$2:$C$38,$A5,Variables!$B$2:$B$38,"P2") -> 2 | D5: =COUNTIFS(Variables!$C$2:$C$38,$A5,Variables!$B$2:$B$38,"P3") -> 0 | E5: =SUM(B5:D5) -> 6 | F5: =COUNTIFS(Variables!$C$2:$C$38,$A5,Variables!$N$2:$N$38,"High") -> 1 | G5: =COUNTIFS(Variables!$C$2:$C$38,$A5,Variables!$N$2:$N$38,"Medium") -> 5 | H5: =COUNTIFS(Variables!$C$2:$C$38,$A5,Variables!$N$2:$N$38,"Low") -> 0
A6: Transfers | B6: =COUNTIFS(Variables!$C$2:$C$38,$A6,Variables!$B$2:$B$38,"P1") -> 2 | C6: =COUNTIFS(Variables!$C$2:$C$38,$A6,Variables!$B$2:$B$38,"P2") -> 5 | D6: =COUNTIFS(Variables!$C$2:$C$38,$A6,Variables!$B$2:$B$38,"P3") -> 0 | E6: =SUM(B6:D6) -> 7 | F6: =COUNTIFS(Variables!$C$2:$C$38,$A6,Variables!$N$2:$N$38,"High") -> 5 | G6: =COUNTIFS(Variables!$C$2:$C$38,$A6,Variables!$N$2:$N$38,"Medium") -> 2 | H6: =COUNTIFS(Variables!$C$2:$C$38,$A6,Variables!$N$2:$N$38,"Low") -> 0
A7: Investments | B7: =COUNTIFS(Variables!$C$2:$C$38,$A7,Variables!$B$2:$B$38,"P1") -> 1 | C7: =COUNTIFS(Variables!$C$2:$C$38,$A7,Variables!$B$2:$B$38,"P2") -> 3 | D7: =COUNTIFS(Variables!$C$2:$C$38,$A7,Variables!$B$2:$B$38,"P3") -> 1 | E7: =SUM(B7:D7) -> 5 | F7: =COUNTIFS(Variables!$C$2:$C$38,$A7,Variables!$N$2:$N$38,"High") -> 1 | G7: =COUNTIFS(Variables!$C$2:$C$38,$A7,Variables!$N$2:$N$38,"Medium") -> 4 | H7: =COUNTIFS(Variables!$C$2:$C$38,$A7,Variables!$N$2:$N$38,"Low") -> 0
A8: Relationship & closures | B8: =COUNTIFS(Variables!$C$2:$C$38,$A8,Variables!$B$2:$B$38,"P1") -> 1 | C8: =COUNTIFS(Variables!$C$2:$C$38,$A8,Variables!$B$2:$B$38,"P2") -> 4 | D8: =COUNTIFS(Variables!$C$2:$C$38,$A8,Variables!$B$2:$B$38,"P3") -> 0 | E8: =SUM(B8:D8) -> 5 | F8: =COUNTIFS(Variables!$C$2:$C$38,$A8,Variables!$N$2:$N$38,"High") -> 2 | G8: =COUNTIFS(Variables!$C$2:$C$38,$A8,Variables!$N$2:$N$38,"Medium") -> 3 | H8: =COUNTIFS(Variables!$C$2:$C$38,$A8,Variables!$N$2:$N$38,"Low") -> 0
A9: Banker | B9: =COUNTIFS(Variables!$C$2:$C$38,$A9,Variables!$B$2:$B$38,"P1") -> 3 | C9: =COUNTIFS(Variables!$C$2:$C$38,$A9,Variables!$B$2:$B$38,"P2") -> 0 | D9: =COUNTIFS(Variables!$C$2:$C$38,$A9,Variables!$B$2:$B$38,"P3") -> 1 | E9: =SUM(B9:D9) -> 4 | F9: =COUNTIFS(Variables!$C$2:$C$38,$A9,Variables!$N$2:$N$38,"High") -> 1 | G9: =COUNTIFS(Variables!$C$2:$C$38,$A9,Variables!$N$2:$N$38,"Medium") -> 2 | H9: =COUNTIFS(Variables!$C$2:$C$38,$A9,Variables!$N$2:$N$38,"Low") -> 1
A10: Complaints & voice of client | B10: =COUNTIFS(Variables!$C$2:$C$38,$A10,Variables!$B$2:$B$38,"P1") -> 2 | C10: =COUNTIFS(Variables!$C$2:$C$38,$A10,Variables!$B$2:$B$38,"P2") -> 1 | D10: =COUNTIFS(Variables!$C$2:$C$38,$A10,Variables!$B$2:$B$38,"P3") -> 1 | E10: =SUM(B10:D10) -> 4 | F10: =COUNTIFS(Variables!$C$2:$C$38,$A10,Variables!$N$2:$N$38,"High") -> 2 | G10: =COUNTIFS(Variables!$C$2:$C$38,$A10,Variables!$N$2:$N$38,"Medium") -> 1 | H10: =COUNTIFS(Variables!$C$2:$C$38,$A10,Variables!$N$2:$N$38,"Low") -> 1
A11: External & composite | B11: =COUNTIFS(Variables!$C$2:$C$38,$A11,Variables!$B$2:$B$38,"P1") -> 1 | C11: =COUNTIFS(Variables!$C$2:$C$38,$A11,Variables!$B$2:$B$38,"P2") -> 0 | D11: =COUNTIFS(Variables!$C$2:$C$38,$A11,Variables!$B$2:$B$38,"P3") -> 1 | E11: =SUM(B11:D11) -> 2 | F11: =COUNTIFS(Variables!$C$2:$C$38,$A11,Variables!$N$2:$N$38,"High") -> 0 | G11: =COUNTIFS(Variables!$C$2:$C$38,$A11,Variables!$N$2:$N$38,"Medium") -> 1 | H11: =COUNTIFS(Variables!$C$2:$C$38,$A11,Variables!$N$2:$N$38,"Low") -> 1
A12: Total | B12: =SUM(B4:B11) -> 16 | C12: =SUM(C4:C11) -> 17 | D12: =SUM(D4:D11) -> 4 | E12: =SUM(E4:E11) -> 37 | F12: =SUM(F4:F11) -> 14 | G12: =SUM(G4:G11) -> 20 | H12: =SUM(H4:H11) -> 3

Sheet Base definitions
A1: Common definitions for all variables
A3: Concept | B3: Definition
A4: t (snapshot_date) | B4: Monthly cut-off date. Every variable uses only information dated ≤ t.
A5: Window (t−W, t] | B5: Period of W days ending at t, excluding day t−W. Example: 30d = the 30 days before the cut-off.
A6: Own baseline (6m) | B6: The client's own average over (t−210d, t−30d]: the prior 6 months, excluding the last month so the recent drop does not contaminate the reference.
A7: Aggregation level | B7: All variables are computed at household level: they add up accounts of all people and linked entities (trusts, LLCs, businesses).
A8: Average daily balance | B8: Average of end-of-day balances for each calendar day in the window (weekends repeat the last business-day balance).
A9: Deposits | B9: Checking, savings, money market and CDs.
A10: AUM | B10: Market value of investment, custody and trust accounts administered by Citizens.
A11: Ex-market AUM | B11: AUMx_d = AUM_d ÷ TWR_Index_d. The index compounds the client portfolio's time-weighted return; dividing by it leaves only changes driven by flows (contributions and withdrawals).
A12: External transfer | B12: Outgoing wire, client-originated ACH to an account at another institution, transfer to the client's own external account, or ACATS. Excludes payments to merchants / billers, taxes, loan payments to Citizens and identified recurring donations.
A13: Internal transfer | B13: Movement between accounts of the same household within Citizens. Never counts as an outflow.
A14: Recurring stream | B14: Credits from the same originator with ≥ 3 occurrences in the identification window and coefficient of variation of intervals < 0.25.
... A19: Alert threshold | B19: Illustrative values to start the scorecard binning and the multi_signal_flag. Recalibrated on Citizens' labeled history (WoE / IV).

Sheet Parameters
A1: Parameters to calibrate with Citizens
A3: Parameter | B3: Initial value | C3: Used in
A4: Days without payroll / pension | B4: 45 days or 1.5× interval | C4: salary / pension / recurring_deposit_stopped_flag
A5: Minimum weight of a recurring stream | B5: 10% of recurring income | C5: recurring_deposit_stopped_flag
A6: Payroll replacement (job change) | B6: ≥ 50% of prior amount | C6: salary_deposit_stopped_flag
A7: Recurring deposit drop | B7: −40% | C7: recurring_deposit_change_pct
A8: External outflows ÷ balance | B8: 15% over 60d | C8: external_transfer_pct_of_balance
A9: Minimum cumulative amount per new destination | B9: $10,000 | C9: new_external_destinations
A10: Outflow baseline floor | B10: $1,000 / month | C10: outflow_vs_baseline_pct
A11: Minimum balance for % | B11: $10,000 | C11: deposit_balance_change_pct, deposit_balance_vs_6m_avg_pct
A12: Reinvestment window | B12: 30 days | C12: fixed_income_maturity_not_reinvested
A13: Internal account consolidation | B13: ≤ 5 days | C13: accounts_closed
A14: Contact cadence | B14: UHNW 30d · HNW 90d (or as agreed) | C14: contact_gap_ratio
... A19: Groups for multi-signal | B19: ≥ 3 of 7 | C19: multi_signal_flag
A21: Blue values = initial team assumptions, pending calibration on Citizens' history.
